dtr_utils/ECD_score.py
dtr_utils/__init__.py
dtr_utils/beam.py
dtr_utils/n_gram_utils.py
dtr_utils/web_ret_utils.py
dtr_utils-0.1.0.dist-info/METADATA
dtr_utils-0.1.0.dist-info/WHEEL
dtr_utils-0.1.0.dist-info/top_level.txt
dtr_utils-0.1.0.dist-info/RECORD
