Metadata-Version: 2.1
Name: dtr-utils
Version: 0.1.0
Summary: Utilities for Decoding Time RAG (DTR) tasks
Author: Rajarshi Roy
Author-email: royrajarshi0123@gmail.com
Classifier: Programming Language :: Python :: 3
Classifier: License :: OSI Approved :: MIT License
Classifier: Operating System :: OS Independent
Requires-Python: >=3.7
Requires-Dist: torch (==1.12.0)
Requires-Dist: transformers (==4.30.0)
Requires-Dist: accelerate (==0.19.0)
Requires-Dist: numpy (==1.23.0)
Requires-Dist: tqdm (==4.64.0)
Requires-Dist: nltk (>=3.6.3)
Requires-Dist: sentence-transformers (>=2.2.0)
Requires-Dist: scikit-learn (>=0.24.2)
Requires-Dist: matplotlib (>=3.4.0)
Requires-Dist: seaborn (>=0.11.0)
Requires-Dist: scipy (>=1.6.0)
Requires-Dist: anytree (>=2.8.0)
Requires-Dist: graphviz (>=0.16)
Requires-Dist: stanza (>=1.4.0)
Requires-Dist: spacy (>=3.0.0)
Requires-Dist: beautifulsoup4 (>=4.9.3)
Requires-Dist: googlesearch-python (==1.2.5)
Requires-Dist: requests (>=2.25.1)
Requires-Dist: lxml (>=4.6.3)
Requires-Dist: pandas (>=1.3.0)
